watchserver/__init__.py
watchserver/__main__.py
watchserver/live.py
watchserver/server.py
watchserver/util.py
watchserver/watch.py
watchserver-0.1.10.dist-info/METADATA
watchserver-0.1.10.dist-info/WHEEL
watchserver-0.1.10.dist-info/entry_points.txt
watchserver-0.1.10.dist-info/RECORD
