Metadata-Version: 2.1
Name: watchserver
Version: 0.1.10
Summary: Python live reload server
Project-URL: Homepage, https://github.com/Tired-Fox/watchserver
Project-URL: Documentation, https://tired-fox.github.io/watchserver
Author-email: Tired Fox <zboehm104@gmail.com>
License-Expression: MIT
Classifier: License :: OSI Approved :: MIT License
Classifier: Operating System :: OS Independent
Classifier: Programming Language :: Python :: 3
Requires-Python: >=3.7
Provides-Extra: dev
Requires-Dist: black; extra == 'dev'
Requires-Dist: isort; extra == 'dev'
Requires-Dist: pylint; extra == 'dev'
Provides-Extra: test
Requires-Dist: pytest; extra == 'test'
